setup.py
pbeauty/__init__.py
pbeauty/__main__.py
pbeauty/_utils.py
pbeauty/cs_encoder.py
pbeauty/decoder.py
pbeauty/descriptor.py
pbeauty/encoder.py
pbeauty/errors.py
pbeauty/example.py
pbeauty/format_encoder.py
pbeauty/py_encoder.py
pbeauty/scanner.py
pbeauty/typedef.py
pbeauty.egg-info/PKG-INFO
pbeauty.egg-info/SOURCES.txt
pbeauty.egg-info/dependency_links.txt
pbeauty.egg-info/top_level.txt