Metadata-Version: 1.1
Name: pbeauty
Version: 10.0
Summary: protobuf parse and beauty tools
Home-page: http://github.com/wstc/pbeauty
Author: Linggui Wang
Author-email: pthread_t@qq.com
License: MIT
Keywords: protobuf,formatbeauty
Platform: UNKNOWN
Classifier: Development Status :: 5 - Production/Stable
Classifier: Environment :: Console
Classifier: Intended Audience :: Developers
Classifier: License :: OSI Approved :: MIT License
Classifier: Operating System :: OS Independent
Classifier: Programming Language :: Python
Classifier: Programming Language :: Python :: 2.7
